phi_tools/__init__.py
phi_tools/db_tools.py
phi_tools/test.py
phi_tools/time_tools.py
phi_tools-0.0.7.dist-info/LICENSE
phi_tools-0.0.7.dist-info/METADATA
phi_tools-0.0.7.dist-info/WHEEL
phi_tools-0.0.7.dist-info/top_level.txt
phi_tools-0.0.7.dist-info/RECORD
